<?xml version="1.0" encoding="utf-8"?>
<Anim>
 <Data id="1" name="Captain_S_IDLE" startFrame="0f" endFrame="100f" />
 <Data id="2" name="Captain_S_arm_kick_right" startFrame="101f" endFrame="126f" />
 <Data id="3" name="Captain_S_boring" startFrame="127f" endFrame="252f" />
 <Data id="4" name="Captain_S_Drinking" startFrame="253f" endFrame="308f" />
 <Data id="5" name="Captain_S_Eating" startFrame="309f" endFrame="429f" />
 <Data id="6" name="Captain_S_Explanation" startFrame="430f" endFrame="475f" />
 <Data id="7" name="Captain_S_Jump_standing" startFrame="476f" endFrame="551f" />
 <Data id="8" name="Captain_S_looking_around" startFrame="552f" endFrame="728f" />
 <Data id="9" name="Captain_S_Pick_object" startFrame="729f" endFrame="769f" />
 <Data id="10" name="Captain_S_pointing_A" startFrame="770f" endFrame="830f" />
 <Data id="11" name="Captain_S_salute" startFrame="831f" endFrame="891f" />
 <Data id="12" name="Captain_S_Say_No" startFrame="892f" endFrame="942f" />
 <Data id="13" name="Captain_S_Shrugs" startFrame="943f" endFrame="988f" />
 <Data id="14" name="Captain_S_sit_down" startFrame="989f" endFrame="1014f" />
 <Data id="15" name="Captain_S_Sitting" startFrame="1015f" endFrame="1065f" />
 <Data id="16" name="Captain_S_Came_up" startFrame="1066f" endFrame="1092f" />
 <Data id="17" name="Captain_S_Talking" startFrame="1093f" endFrame="1138f" />
 <Data id="18" name="Captain_S_Talking_B" startFrame="1139f" endFrame="1274f" />
 <Data id="19" name="Captain_S_Use_object" startFrame="1275f" endFrame="1315f" />
 <Data id="20" name="Captain_S_warning" startFrame="1316f" endFrame="1376f" />
 <Data id="21" name="Captain_S_waving" startFrame="1377f" endFrame="1422f" />
 <Data id="22" name="Captain_M_Climbing_abyss_idle" startFrame="1427f" endFrame="1502f" />
 <Data id="23" name="Captain_M_Climbing_abyss_left" startFrame="1507f" endFrame="1532f" />
 <Data id="24" name="Captain_M_Climbing_abyss_right" startFrame="1537f" endFrame="1562f" />
 <Data id="25" name="Captain_M_Climbing_ladder_down" startFrame="1567f" endFrame="1607f" />
 <Data id="26" name="Captain_M_Climbing_ladder_up" startFrame="1612f" endFrame="1652f" />
 <Data id="27" name="Captain_M_Climbing_rope" startFrame="1657f" endFrame="1687f" />
 <Data id="28" name="Captain_M_falling_down" startFrame="1692f" endFrame="1732f" />
 <Data id="29" name="Captain_M_fly_forward" startFrame="1737f" endFrame="1837f" />
 <Data id="30" name="Captain_M_fly_left" startFrame="1842f" endFrame="1942f" />
 <Data id="31" name="Captain_M_fly_right" startFrame="1947f" endFrame="2047f" />
 <Data id="32" name="Captain_M_making_item" startFrame="2052f" endFrame="2082f" />
 <Data id="33" name="Captain_M_Moving_left" startFrame="2087f" endFrame="2107f" />
 <Data id="34" name="Captain_M_Moving_right" startFrame="2108f" endFrame="2128f" />
 <Data id="35" name="Captain_M_sleeping" startFrame="2133f" endFrame="2208f" />
 <Data id="36" name="Captain_M_Sneaking" startFrame="2213f" endFrame="2263f" />
 <Data id="37" name="Captain_M_Swimming" startFrame="2268f" endFrame="2298f" />
 <Data id="38" name="Captain_F_Puting_Weapons_back" startFrame="2303f" endFrame="2353f" />
 <Data id="39" name="Captain_F_Taking_weapons_out" startFrame="2354f" endFrame="2399f" />
 <Data id="40" name="Captain_F_COMBAT_mode_staynig" startFrame="2400f" endFrame="2450f" />
 <Data id="41" name="Captain_F_FromStand_toSquat_A" startFrame="2451f" endFrame="2491f" />
 <Data id="42" name="Captain_F_COMBAT_mode_squat" startFrame="2492f" endFrame="2542f" />
 <Data id="43" name="Captain_F_fire_Squat" startFrame="2547f" endFrame="2584f" />
 <Data id="44" name="Captain_F_lookingAround_Squat" startFrame="2585f" endFrame="2670f" />
 <Data id="45" name="Captain_F_Reload_squat" startFrame="2671f" endFrame="2756f" />
 <Data id="46" name="Captain_F_FromSquatA_toStaing" startFrame="2761f" endFrame="2798f" />
 <Data id="47" name="Captain_F_dodge_to_left" startFrame="2799f" endFrame="2834f" />
 <Data id="48" name="Captain_F_dodge_to_right" startFrame="2835f" endFrame="2870f" />
 <Data id="49" name="Captain_F_duck_below_high_swing" startFrame="2871f" endFrame="2906f" />
 <Data id="50" name="Captain_F_Hit_from_back" startFrame="2907f" endFrame="2942f" />
 <Data id="51" name="Captain_F_Hit_from_front" startFrame="2943f" endFrame="2978f" />
 <Data id="52" name="Captain_F_Hit_from_left" startFrame="2979f" endFrame="3014f" />
 <Data id="53" name="Captain_F_Hit_from_righ" startFrame="3015f" endFrame="3050f" />
 <Data id="54" name="Captain_F_L_parry_from_stright_down" startFrame="3051f" endFrame="3086f" />
 <Data id="55" name="Captain_F_L_parry_high_left" startFrame="3087f" endFrame="3122f" />
 <Data id="56" name="Captain_F_L_parry_mid_front" startFrame="3123f" endFrame="3158f" />
 <Data id="57" name="Captain_F_L_swing_high_left" startFrame="3159f" endFrame="3194f" />
 <Data id="58" name="Captain_F_L_swing_high_right" startFrame="3195f" endFrame="3230f" />
 <Data id="59" name="Captain_F_L_swing_high_straight_down" startFrame="3231f" endFrame="3266f" />
 <Data id="60" name="Captain_F_L_swing_low_left" startFrame="3267f" endFrame="3302f" />
 <Data id="61" name="Captain_F_L_swing_low_right" startFrame="3303f" endFrame="3338f" />
 <Data id="62" name="Captain_F_L_thrust_high" startFrame="3339f" endFrame="3374f" />
 <Data id="63" name="Captain_F_L_thrust_low" startFrame="3375f" endFrame="3410f" />
 <Data id="64" name="Captain_F_L_thrust_mid" startFrame="3411f" endFrame="3446f" />
 <Data id="65" name="Captain_F_LeftFoot_Kick" startFrame="3447f" endFrame="3477f" />
 <Data id="66" name="Captain_F_Looking_around_staying" startFrame="3478f" endFrame="3563f" />
 <Data id="67" name="Captain_F_RightFoot_kick" startFrame="3564f" endFrame="3594f" />
 <Data id="68" name="Captain_F_fire_staying" startFrame="3599f" endFrame="3636f" />
 <Data id="69" name="Captain_F_Reload_gun_staying" startFrame="3637f" endFrame="3722f" />
 <Data id="70" name="Captain_F_Knocked_backward" startFrame="3727f" endFrame="3767f" />
 <Data id="71" name="Captain_F_Down_back" startFrame="3768f" endFrame="3808f" />
 <Data id="72" name="Captain_F_Recover_from_knocked_backward" startFrame="3809f" endFrame="3849f" />
 <Data id="73" name="Captain_F_Knocked_forward" startFrame="3850f" endFrame="3878f" />
 <Data id="74" name="Captain_F_Down_forward" startFrame="3879f" endFrame="3919f" />
 <Data id="75" name="Captain_F_Recover_from_knocked_forward" startFrame="3920f" endFrame="3952f" />
 <Data id="76" name="Captain_FM_Casual_walk" startFrame="3957f" endFrame="3993f" />
 <Data id="77" name="Captain_FM_Cautious_walk" startFrame="3998f" endFrame="4038f" />
 <Data id="78" name="Captain_FM_Fire_walk" startFrame="4043f" endFrame="4083f" />
 <Data id="79" name="Captain_FM_Combat_run" startFrame="4088f" endFrame="4114f" />
 <Data id="80" name="Captain_FM_Fire_run" startFrame="4119f" endFrame="4145f" />
 <Data id="81" name="Captain_FM_run" startFrame="4150f" endFrame="4176f" />
 <Data id="82" name="Captain_FM_Jump_runing" startFrame="4181f" endFrame="4221f" />
 <Data id="83" name="Captain_FM_Fire_walking_back" startFrame="4226f" endFrame="4261f" />
 <Data id="84" name="Captain_FM_Walking_back" startFrame="4266f" endFrame="4301f" />
 <Data id="85" name="Captain_FM_Die_knocked_backward" startFrame="4306f" endFrame="4323f" />
 <Data id="86" name="Captain_FM_Die_knocked_forward" startFrame="4328f" endFrame="4345f" />
 <Data id="87" name="Captain_FM_Die_on_back" startFrame="4350f" endFrame="4388f" />
 <Data id="88" name="Captain_FM_Die_on_belt" startFrame="4393f" endFrame="4500f" />
 <Data id="89" name="Captain_FM_Die_squat" startFrame="4505f" endFrame="4538f" />
</Anim>